ciscoaplookup/__init__.py
ciscoaplookup/countries.py
ciscoaplookup/juniper.py
ciscoaplookup/logic.py
test/__init__.py
test/test_ciscoaplookup.py
ciscoaplookup-0.10.0.dist-info/LICENSE
ciscoaplookup-0.10.0.dist-info/METADATA
ciscoaplookup-0.10.0.dist-info/WHEEL
ciscoaplookup-0.10.0.dist-info/top_level.txt
ciscoaplookup-0.10.0.dist-info/RECORD
