Metadata-Version: 2.1
Name: ciscoaplookup
Version: 0.10.0
Summary: The Cisco Wireless LAN Compliance Lookup library
Home-page: https://github.com/steffenschumacher/ciscoaplookup.git
Author: Steffen Schumacher
Author-email: ssch@wheel.dk
License: UNKNOWN
Platform: UNKNOWN
Classifier: Programming Language :: Python :: 3
Classifier: License :: OSI Approved :: MIT License
Classifier: Operating System :: OS Independent
Requires-Dist: requests
Requires-Dist: xlrd (==1.2.0)
Requires-Dist: beautifulsoup4
Requires-Dist: country-converter
